{"dims": ["N_LEVELS"], "attrs": {"whp_name": "DELHE3", "whp_unit": "PERCNT", "units": "percent", "ancillary_variables": "delta_helium_3_qc delta_helium_3_error"}, "data": [NaN, NaN, NaN, NaN, NaN, NaN, NaN, NaN, NaN, NaN, NaN, NaN, NaN, NaN, NaN, NaN, NaN, NaN, NaN, NaN, NaN, NaN, NaN, NaN], "coords": {"pressure": {"dims": ["N_LEVELS"], "attrs": {"whp_name": "CTDPRS", "whp_unit": "DBAR", "standard_name": "sea_water_pressure", "units": "dbar", "axis": "Z", "positive": "down"}, "data": [20.9, 20.9, 40.4, 40.4, 40.5, 40.5, 61.0, 61.0, 80.3, 80.3, 100.7, 100.7, 151.2, 176.2, 201.2, 201.2, 249.9, 250.0, 250.1, 300.5, 400.6, 451.4, 500.0, 602.4]}, "latitude": {"dims": [], "attrs": {"whp_name": "LATITUDE", "standard_name": "latitude", "units": "degree_north", "axis": "Y"}, "data": -63.7352}, "longitude": {"dims": [], "attrs": {"whp_name": "LONGITUDE", "standard_name": "longitude", "units": "degree_east", "axis": "X"}, "data": -50.8435}, "time": {"dims": [], "attrs": {"standard_name": "time", "axis": "T", "whp_name": ["DATE", "TIME"], "resolution": 0.000694}, "data": "1996-05-07T11:12:00"}, "expocode": {"dims": [], "attrs": {"whp_name": "EXPOCODE"}, "data": "06AQANTXIII_4"}, "station": {"dims": [], "attrs": {"whp_name": "STNNBR"}, "data": "99"}, "cast": {"dims": [], "attrs": {"whp_name": "CASTNO"}, "data": 1}, "sample": {"dims": ["N_LEVELS"], "attrs": {"whp_name": "SAMPNO"}, "data": ["23", "22", "21", "20", "19", "18", "17", "16", "15", "14", "13", "12", "11", "10", "9", "8", "7", "6", "5", "4", "3", "2", "1", "24"]}}, "name": "delta_helium_3"}