{"dims": ["N_LEVELS"], "attrs": {"whp_name": "OXYGEN", "whp_unit": "UMOL/KG", "standard_name": "moles_of_oxygen_per_unit_mass_in_sea_water", "units": "umol/kg", "ancillary_variables": "oxygen_qc"}, "data": [363.8999938964844, 353.20001220703125, 348.70001220703125, 346.79998779296875, 346.5, 336.1000061035156, 332.8999938964844, 322.1000061035156, 322.70001220703125, 324.0, 322.20001220703125, 319.29998779296875, NaN, NaN, NaN, NaN, NaN, NaN, NaN, NaN, NaN, NaN, NaN, NaN], "coords": {"pressure": {"dims": ["N_LEVELS"], "attrs": {"whp_name": "CTDPRS", "whp_unit": "DBAR", "standard_name": "sea_water_pressure", "units": "dbar", "axis": "Z", "positive": "down"}, "data": [9.4, 48.6, 99.1, 149.7, 200.1, 249.0, 298.9, 398.9, 499.5, 600.0, 701.0, 760.8, NaN, NaN, NaN, NaN, NaN, NaN, NaN, NaN, NaN, NaN, NaN, NaN]}, "latitude": {"dims": [], "attrs": {"whp_name": "LATITUDE", "standard_name": "latitude", "units": "degree_north", "axis": "Y"}, "data": -69.3565}, "longitude": {"dims": [], "attrs": {"whp_name": "LONGITUDE", "standard_name": "longitude", "units": "degree_east", "axis": "X"}, "data": 74.5762}, "time": {"dims": [], "attrs": {"standard_name": "time", "axis": "T", "whp_name": ["DATE", "TIME"], "resolution": 0.000694}, "data": "2001-02-20T14:53:00"}, "expocode": {"dims": [], "attrs": {"whp_name": "EXPOCODE"}, "data": "09AR20010101"}, "station": {"dims": [], "attrs": {"whp_name": "STNNBR"}, "data": "91"}, "cast": {"dims": [], "attrs": {"whp_name": "CASTNO"}, "data": 1}, "sample": {"dims": ["N_LEVELS"], "attrs": {"whp_name": "SAMPNO"}, "data": ["12", "11", "10", "9", "8", "7", "6", "5", "4", "3", "2", "1", "", "", "", "", "", "", "", "", "", "", "", ""]}}, "name": "oxygen"}