{"dims": ["N_LEVELS"], "attrs": {"whp_name": "THETA", "whp_unit": "DEG C", "standard_name": "sea_water_potential_temperature", "units": "degC", "reference_scale": "unknown"}, "data": [-0.052000001072883606, -0.04800000041723251, -0.07400000095367432, -0.07100000232458115, -0.06199999898672104, -0.05999999865889549, -0.5019999742507935, -0.531000018119812, -0.6050000190734863, -0.6050000190734863, -0.6669999957084656, -1.0490000247955322, -1.38100004196167, -1.375, -1.5429999828338623, -1.527999997138977, -1.4509999752044678, -1.4579999446868896, -1.1970000267028809, -0.9449999928474426, -0.9509999752044678, 0.125, 0.5329999923706055, 0.6859999895095825], "coords": {"pressure": {"dims": ["N_LEVELS"], "attrs": {"whp_name": "CTDPRS", "whp_unit": "DBAR", "standard_name": "sea_water_pressure", "units": "dbar", "axis": "Z", "positive": "down"}, "data": [15.5, 15.6, 15.6, 15.6, 15.6, 15.7, 31.0, 44.7, 60.3, 60.4, 74.6, 91.2, 104.5, 104.9, 121.1, 134.9, 150.2, 150.3, 175.6, 201.1, 201.7, 300.5, 402.0, 500.6]}, "latitude": {"dims": [], "attrs": {"whp_name": "LATITUDE", "standard_name": "latitude", "units": "degree_north", "axis": "Y"}, "data": -66.5008}, "longitude": {"dims": [], "attrs": {"whp_name": "LONGITUDE", "standard_name": "longitude", "units": "degree_east", "axis": "X"}, "data": 64.0782}, "time": {"dims": [], "attrs": {"standard_name": "time", "axis": "T", "whp_name": ["DATE", "TIME"], "resolution": 0.000694}, "data": "2001-01-16T23:18:00"}, "expocode": {"dims": [], "attrs": {"whp_name": "EXPOCODE"}, "data": "09AR20010101"}, "station": {"dims": [], "attrs": {"whp_name": "STNNBR"}, "data": "14"}, "cast": {"dims": [], "attrs": {"whp_name": "CASTNO"}, "data": 1}, "sample": {"dims": ["N_LEVELS"], "attrs": {"whp_name": "SAMPNO"}, "data": ["19", "24", "22", "21", "20", "23", "18", "17", "16", "15", "14", "13", "11", "12", "10", "9", "7", "8", "6", "4", "5", "3", "2", "1"]}}, "name": "potential_temperature_c"}