{"dims": ["N_LEVELS"], "attrs": {"whp_name": "THETA", "whp_unit": "DEG C", "standard_name": "sea_water_potential_temperature", "units": "degC", "reference_scale": "unknown"}, "data": [0.4717999994754791, 0.41179999709129333, 0.33090001344680786, 0.33230000734329224, 0.33410000801086426, 0.21279999613761902, 0.08070000261068344, -0.02810000069439411, -0.12030000239610672, -0.26089999079704285, -0.2621999979019165, -0.262800008058548, -0.2630999982357025, -0.32019999623298645, -0.3580999970436096, -0.3659000098705292, -0.3783999979496002, -0.37689998745918274, -0.37689998745918274, -0.3856000006198883, -0.3919000029563904, -0.3935000002384186, -0.3944999873638153, -0.39430001378059387], "coords": {"pressure": {"dims": ["N_LEVELS"], "attrs": {"whp_name": "CTDPRS", "whp_unit": "DBAR", "standard_name": "sea_water_pressure", "units": "dbar", "axis": "Z", "positive": "down"}, "data": [751.7, 850.4, 1001.7, 1002.2, 1002.4, 1251.1, 1499.7, 1751.1, 2000.9, 2500.8, 2501.6, 2501.9, 2502.1, 2750.6, 2999.9, 3150.7, 3259.9, 3260.2, 3260.4, 3309.9, 3358.5, 3358.7, 3358.8, 3359.0]}, "latitude": {"dims": [], "attrs": {"whp_name": "LATITUDE", "standard_name": "latitude", "units": "degree_north", "axis": "Y"}, "data": -69.0152}, "longitude": {"dims": [], "attrs": {"whp_name": "LONGITUDE", "standard_name": "longitude", "units": "degree_east", "axis": "X"}, "data": -0.0025}, "time": {"dims": [], "attrs": {"standard_name": "time", "axis": "T", "whp_name": ["DATE", "TIME"], "resolution": 0.000694}, "data": "1996-04-21T20:47:59.999999"}, "expocode": {"dims": [], "attrs": {"whp_name": "EXPOCODE"}, "data": "06AQANTXIII_4"}, "station": {"dims": [], "attrs": {"whp_name": "STNNBR"}, "data": "62"}, "cast": {"dims": [], "attrs": {"whp_name": "CASTNO"}, "data": 3}, "sample": {"dims": ["N_LEVELS"], "attrs": {"whp_name": "SAMPNO"}, "data": ["23", "22", "19", "20", "21", "18", "17", "16", "15", "11", "12", "13", "14", "10", "9", "8", "5", "6", "7", "4", "3", "2", "1", "24"]}}, "name": "potential_temperature_c"}