{"dims": [], "attrs": {"whp_name": "SECT_ID"}, "data": "S04", "coords": {"latitude": {"dims": [], "attrs": {"whp_name": "LATITUDE", "standard_name": "latitude", "units": "degree_north", "axis": "Y"}, "data": -66.5018}, "longitude": {"dims": [], "attrs": {"whp_name": "LONGITUDE", "standard_name": "longitude", "units": "degree_east", "axis": "X"}, "data": -0.0002}, "time": {"dims": [], "attrs": {"standard_name": "time", "axis": "T", "whp_name": ["DATE", "TIME"], "resolution": 0.000694}, "data": "1996-04-20T01:04:00"}, "expocode": {"dims": [], "attrs": {"whp_name": "EXPOCODE"}, "data": "06AQANTXIII_4"}, "station": {"dims": [], "attrs": {"whp_name": "STNNBR"}, "data": "57"}, "cast": {"dims": [], "attrs": {"whp_name": "CASTNO"}, "data": 1}}, "name": "section_id"}