{"dims": ["N_LEVELS"], "attrs": {"whp_name": "BTLNBR", "ancillary_variables": "bottle_number_qc"}, "data": ["8", "7", "6", "5", "4", "3", "2", "1"], "coords": {"pressure": {"dims": ["N_LEVELS"], "attrs": {"whp_name": "CTDPRS", "whp_unit": "DBAR", "standard_name": "sea_water_pressure", "units": "dbar", "axis": "Z", "positive": "down"}, "data": [1.3, 22.0, 40.8, 200.3, 400.1, 599.8, 801.6, 1001.1]}, "latitude": {"dims": [], "attrs": {"whp_name": "LATITUDE", "standard_name": "latitude", "units": "degree_north", "axis": "Y"}, "data": -3.0}, "longitude": {"dims": [], "attrs": {"whp_name": "LONGITUDE", "standard_name": "longitude", "units": "degree_east", "axis": "X"}, "data": -110.0}, "time": {"dims": [], "attrs": {"standard_name": "time", "axis": "T", "whp_name": ["DATE", "TIME"], "resolution": 0.000694}, "data": "2004-11-20T01:52:00"}, "expocode": {"dims": [], "attrs": {"whp_name": "EXPOCODE"}, "data": "33RBGP604_1"}, "station": {"dims": [], "attrs": {"whp_name": "STNNBR"}, "data": "44"}, "cast": {"dims": [], "attrs": {"whp_name": "CASTNO"}, "data": 1}, "sample": {"dims": ["N_LEVELS"], "attrs": {"whp_name": "SAMPNO"}, "data": ["8", "7", "6", "5", "4", "3", "2", "1"]}}, "name": "bottle_number"}